log_kbots/__init__.py
log_kbots-1.0.0.dist-info/LICENSE.txt
log_kbots-1.0.0.dist-info/METADATA
log_kbots-1.0.0.dist-info/WHEEL
log_kbots-1.0.0.dist-info/top_level.txt
log_kbots-1.0.0.dist-info/RECORD
