Metadata-Version: 2.1
Name: log-kbots
Version: 1.0.0
Summary: UNKNOWN
Home-page: https://github.com/kbots-dga-kroton/log_kbots
Author: Bruno Nascimento
Author-email: bruno_freddy@hotmail.com
License: MIT
Project-URL: Código fonte, https://github.com/kbots-dga-kroton/log_kbots
Project-URL: Download, https://github.com/kbots-dga-kroton/log_kbots/archive/main.zip
Keywords: log_kbots,kbots,kroton
Platform: UNKNOWN
Classifier: Development Status :: 5 - Production/Stable
Classifier: Intended Audience :: Developers
Classifier: License :: OSI Approved :: MIT License
Classifier: Natural Language :: Portuguese (Brazilian)
Classifier: Operating System :: OS Independent
Classifier: Topic :: Software Development :: Internationalization
Requires-Python: >=3.6
